aurora/__init__.py
aurora/_version.py
aurora/area.py
aurora/batch.py
aurora/normalisation.py
aurora/rollout.py
aurora/tracker.py
aurora/foundry/__init__.py
aurora/foundry/client/__init__.py
aurora/foundry/client/api.py
aurora/foundry/client/foundry.py
aurora/foundry/common/__init__.py
aurora/foundry/common/channel.py
aurora/foundry/common/model.py
aurora/foundry/demo/__init__.py
aurora/foundry/demo/hres_t0_data.py
aurora/foundry/demo/interactive.py
aurora/foundry/server/mlflow_wrapper.py
aurora/model/__init__.py
aurora/model/aurora.py
aurora/model/compat.py
aurora/model/decoder.py
aurora/model/encoder.py
aurora/model/film.py
aurora/model/fourier.py
aurora/model/levelcond.py
aurora/model/lora.py
aurora/model/patchembed.py
aurora/model/perceiver.py
aurora/model/posencoding.py
aurora/model/swin3d.py
aurora/model/util.py
docs/aurora.jpg
microsoft_aurora-1.8.0.dist-info/METADATA
microsoft_aurora-1.8.0.dist-info/WHEEL
microsoft_aurora-1.8.0.dist-info/licenses/LICENSE.txt
microsoft_aurora-1.8.0.dist-info/RECORD
