Metadata-Version: 2.4
Name: microsoft-aurora
Version: 1.8.0
Summary: Implementation of the Aurora model
Project-URL: repository, https://github.com/microsoft/aurora
Author-email: Cris Bodnar <crisbodnar96@gmail.com>, Wessel Bruinsma <wbruinsma@microsoft.com>, Ana Lucic <ana.lucic@microsoft.com>, Megan Stanley <meganstanley@microsoft.com>, Patrick Garvan <pgarvan@microsoft.com>, Johannes Brandstetter <brandstetter@ml.jku.at>, "Richard E. Turner" <t-rturner@microsoft.com>, Paris Perdikaris <paperdikaris@microsoft.com>
License: MIT License
License-File: LICENSE.txt
Keywords: atmospheric chemistry,atmospheric dynamics,aurora model,foundation models,ocean waves,tropical cyclone tracking,weather prediction
Classifier: Development Status :: 5 - Production/Stable
Classifier: Programming Language :: Python :: 3
Requires-Python: >=3.10
Requires-Dist: azure-storage-blob
Requires-Dist: einops
Requires-Dist: huggingface-hub
Requires-Dist: netcdf4
Requires-Dist: numpy
Requires-Dist: pydantic
Requires-Dist: scipy
Requires-Dist: timm
Requires-Dist: torch
Requires-Dist: xarray
Provides-Extra: dev
Requires-Dist: build; extra == 'dev'
Requires-Dist: ghp-import; extra == 'dev'
Requires-Dist: jupyter-book; extra == 'dev'
Requires-Dist: mlflow; extra == 'dev'
Requires-Dist: mypy; extra == 'dev'
Requires-Dist: pre-commit; extra == 'dev'
Requires-Dist: pytest; extra == 'dev'
Requires-Dist: pytest-cov; extra == 'dev'
Requires-Dist: requests-mock; extra == 'dev'
Requires-Dist: ruff==0.4.1; extra == 'dev'
Requires-Dist: wheel; extra == 'dev'
